CONTRIBUTORS
COPYING
MANIFEST.in
README.rst
pristine-lfs.rst
setup.cfg
setup.py
pristine_lfs/__init__.py
pristine_lfs/errors.py
pristine_lfs/gitwrap.py
pristine_lfs/gitwrap.pyi
pristine_lfs/log.py
pristine_lfs/main.py
pristine_lfs/util.py
pristine_lfs.egg-info/PKG-INFO
pristine_lfs.egg-info/SOURCES.txt
pristine_lfs.egg-info/dependency_links.txt
pristine_lfs.egg-info/entry_points.txt
pristine_lfs.egg-info/requires.txt
pristine_lfs.egg-info/top_level.txt
stubs/sh.pyi
stubs/sh/contrib.pyi
tests/conftest.py
tests/test_checkout.py
tests/test_commit.py
tests/test_git_works.py
tests/test_import_dsc.py
tests/test_list.py
tests/test_verify.py