Metadata-Version: 2.1
Name: pristine-lfs
Version: 20241219.0
Summary: a pristine-tar replacement that works with Git LFS
Home-page: https://salsa.debian.org/pristine-lfs-team/pristine-lfs
Author: Andrej Shadura
Author-email: andrew.shadura@collabora.co.uk
License: GPL-2+
Classifier: Development Status :: 4 - Beta
Classifier: Environment :: Console
Classifier: Intended Audience :: Developers
Classifier: License :: OSI Approved :: GNU General Public License (GPL)
Classifier: License :: OSI Approved :: GNU General Public License v2 or later (GPLv2+)
Classifier: Operating System :: OS Independent
Classifier: Programming Language :: Python
Classifier: Programming Language :: Python :: 3.7
Classifier: Programming Language :: Python :: 3.8
Classifier: Programming Language :: Python :: 3.9
Classifier: Programming Language :: Python :: 3.10
Classifier: Programming Language :: Python :: 3.11
Classifier: Programming Language :: Python :: 3.12
Classifier: Programming Language :: Python :: 3.13
Classifier: Topic :: Software Development :: Build Tools
Classifier: Topic :: Software Development :: Version Control :: Git
Requires-Python: >=3.7
Provides-Extra: test
License-File: COPYING
